LICENSE
MANIFEST.in
README.rst
setup.py
google/__init__.py
google/cloud/__init__.py
google/cloud/grpc/__init__.py
google/cloud/grpc/datastore/__init__.py
google/cloud/grpc/datastore/v1/__init__.py
google/cloud/grpc/datastore/v1/datastore_pb2.py
google/cloud/grpc/datastore/v1/datastore_pb2_grpc.py
google/cloud/grpc/datastore/v1/entity_pb2.py
google/cloud/grpc/datastore/v1/entity_pb2_grpc.py
google/cloud/grpc/datastore/v1/query_pb2.py
google/cloud/grpc/datastore/v1/query_pb2_grpc.py
grpc_google_cloud_datastore_v1.egg-info/PKG-INFO
grpc_google_cloud_datastore_v1.egg-info/SOURCES.txt
grpc_google_cloud_datastore_v1.egg-info/dependency_links.txt
grpc_google_cloud_datastore_v1.egg-info/namespace_packages.txt
grpc_google_cloud_datastore_v1.egg-info/requires.txt
grpc_google_cloud_datastore_v1.egg-info/top_level.txt